<?xml version = '1.0' encoding = 'UTF-8'?>
<FKArc class="oracle.dbtools.crest.model.design.relational.FKArc" directorySegmentName="seg_0" id="FB0B39BE-5023-E92F-00E6-0ECD1143B45B" name="FKArc_2">
<createdBy>Walter Rivera H</createdBy>
<createdTime>2021-05-20 12:21:43 UTC</createdTime>
<ownerDesignName>Proyecto_OBL</ownerDesignName>
<mandatory>false</mandatory>
<reverseArc>true</reverseArc>
<table>E7AFE517-D30B-8BB0-56D3-2C97987894B8</table>
<fkeys>
<fkeyID>899CCCDE-5F6D-A048-F6CA-D19FB3217BC8</fkeyID>
<fkeyID>5AEB0911-7BC1-2EB4-1D34-9F8A5D29FA14</fkeyID>
</fkeys>
</FKArc>
